{
    "Global Noodle": {
        "Mon": [
            "장칼국수",
            "추가밥",
            "새우까스&감자튀김",
            "콩나물무침",
            "배추김치"
        ],
        "Tue": [
            "잔치국수",
            "후리가케밥",
            "왕만두찜/요구르트",
            "오복채무침",
            "배추김치"
        ],
        "Wed": [
            "자장면",
            "추가밥/팽이장국",
            "모듬탕수육",
            "단무지짜사이",
            "배추김치"
        ],
        "Thu": [
            "돈코츠라멘",
            "추가밥",
            "만두오꼬노미야끼",
            "오이지무침",
            "깍두기"
        ],
        "Fri": [
            "물비빔막국수",
            "김가루밥/유부우동국",
            "미니메밀전병&동그랑땡",
            "콘마카로니샐러드",
            "배추김치"
        ]
    },
    "One Plate": {
        "Mon": [
            "(뚝)돼지불고기",
            "쌀밥",
            "비엔나케찹볶음",
            "콩나물무침",
            "배추김치"
        ],
        "Tue": [
            "김치오므라이스",
            "미역장국",
            "투움바함박스테이크",
            "오복채무침",
            "배추김치"
        ],
        "Wed": [
            "베이컨갈릭볶음밥*소시지1/2",
            "팽이장국",
            "닭꼬치",
            "단무지짜사이",
            "배추김치"
        ],
        "Thu": [
            "제육김치덮밥",
            "어묵국",
            "허니버터회오리감자",
            "오이지무침",
            "깍두기"
        ],
        "Fri": [
            "고구마치즈돈까스",
            "추가밥/유부우동국",
            "요거트맛푸딩",
            "콘마카로니샐러드",
            "배추김치"
        ]
    }
}